integration.py
license_scanner/__init__.py
license_scanner/__main__.py
license_scanner/cli.py
license_scanner/get_all_licenses.py
license_scanner/get_all_packages/__init__.py
license_scanner/get_all_packages/main.py
license_scanner/parse_license/__init__.py
license_scanner/parse_license/licenses_synonyms.py
license_scanner/parse_license/main.py
license_scanner/spdx_logic/__init__.py
license_scanner/spdx_logic/main.py
license_scanner-0.4.4.dist-info/METADATA
license_scanner-0.4.4.dist-info/WHEEL
license_scanner-0.4.4.dist-info/entry_points.txt
license_scanner-0.4.4.dist-info/RECORD
