Metadata-Version: 2.4
Name: license_scanner
Version: 0.4.4
Project-URL: homepage, https://github.com/wagenrace/license_scanner
Project-URL: documentation, https://github.com/wagenrace/license_scanner
Project-URL: source, https://github.com/wagenrace/license_scanner
Project-URL: download, https://pypi.org/project/license_scanner/#files
Project-URL: tracker, https://github.com/wagenrace/license_scanner/issues
Project-URL: release notes, https://github.com/wagenrace/license_scanner/blob/main/HISTORY.md
Author-email: Tom Nijhof-Verhees <nijhof.dns@gmail.com>
License-Expression: MIT
Keywords: checker,license,scanner
Classifier: Development Status :: 4 - Beta
Classifier: Environment :: Console
Classifier: Intended Audience :: Developers
Classifier: Intended Audience :: System Administrators
Classifier: License :: OSI Approved :: MIT License
Classifier: Operating System :: OS Independent
Classifier: Programming Language :: Python
Classifier: Programming Language :: Python :: 3
Classifier: Programming Language :: Python :: 3 :: Only
Classifier: Programming Language :: Python :: 3.8
Classifier: Programming Language :: Python :: 3.9
Classifier: Programming Language :: Python :: 3.10
Classifier: Programming Language :: Python :: 3.11
Classifier: Programming Language :: Python :: 3.12
Classifier: Programming Language :: Python :: 3.13
Classifier: Programming Language :: Python :: 3.14
Requires-Python: >=3.8
Requires-Dist: tomli>=1.1.0; python_version < '3.11'
